{"id":"2025-12-13__friday-super-formula-r2-us","date":"2025-12-13","name":"Friday Super Formula R2 US","participants":9,"races":[{"tier":"3x3","strength_of_field":1063.98,"winner":{"slug":"garnet-cobra-yt","driver":"garnet_cobra YT"},"podium":[{"pos":1,"slug":"garnet-cobra-yt","driver":"garnet_cobra YT","points":7,"dsr_gain":3.5},{"pos":2,"slug":"trc-3ggm4n","driver":"TRC_3GGM4N","points":5.75,"dsr_gain":8.88},{"pos":3,"slug":"heloskickass-vr","driver":"Heloskickass_VR","points":5,"dsr_gain":0.5}],"results":[{"pos":1,"slug":"garnet-cobra-yt","driver":"garnet_cobra YT","points":7,"dsr_gain":3.5},{"pos":2,"slug":"trc-3ggm4n","driver":"TRC_3GGM4N","points":5.75,"dsr_gain":8.88},{"pos":3,"slug":"heloskickass-vr","driver":"Heloskickass_VR","points":5,"dsr_gain":0.5},{"pos":4,"slug":"trc-sherkain","driver":"TRC_Sherkain","points":4.5,"dsr_gain":2.25},{"pos":5,"slug":"c-fang","driver":"C. Fang","points":4,"dsr_gain":-2},{"pos":6,"slug":"shaolin-trunk","driver":"Shaolin Trunk","points":3.5,"dsr_gain":1.75},{"pos":7,"slug":"jay","driver":"Jay","points":3,"dsr_gain":3.5},{"pos":8,"slug":"juancho","driver":"Juancho","points":2.5,"dsr_gain":-0.75},{"pos":9,"slug":"monkey-d-luffy","driver":"Monkey D Luffy","points":2,"dsr_gain":1}],"biggest_dsr_gain":{"slug":"trc-3ggm4n","driver":"TRC_3GGM4N","value":8.88}}]}