{"id":"2026-02-16__m2-cup-round-1-red-bull-ring-eu","date":"2026-02-16","name":"M2 Cup - Round 1 - Red Bull Ring - EU","participants":15,"races":[{"tier":"Cup","strength_of_field":1064.84,"winner":{"slug":"jhkizzle","driver":"jhkizzle"},"podium":[{"pos":1,"slug":"jhkizzle","driver":"jhkizzle","points":14,"dsr_gain":13},{"pos":2,"slug":"shadowsboxing","driver":"Shadowsboxing","points":11.5,"dsr_gain":11.75},{"pos":3,"slug":"some-guy","driver":"Some Guy","points":10,"dsr_gain":5}],"results":[{"pos":1,"slug":"jhkizzle","driver":"jhkizzle","points":14,"dsr_gain":13},{"pos":2,"slug":"shadowsboxing","driver":"Shadowsboxing","points":11.5,"dsr_gain":11.75},{"pos":3,"slug":"some-guy","driver":"Some Guy","points":10,"dsr_gain":5},{"pos":4,"slug":"trc-e-grigolon","driver":"TRC E. Grigolon","points":9,"dsr_gain":10.5},{"pos":5,"slug":"walter","driver":"Walter","points":8,"dsr_gain":16},{"pos":6,"slug":"piece-duke","driver":"piece-duke","points":7,"dsr_gain":17.5},{"pos":7,"slug":"p-zebra","driver":"P. Zebra","points":6,"dsr_gain":7},{"pos":8,"slug":"sauce-sangoma-23","driver":"Sauce_Sangoma 23","points":5,"dsr_gain":-9.5},{"pos":9,"slug":"ian","driver":"Ian","points":4,"dsr_gain":-4},{"pos":10,"slug":"trc-3ggm4n","driver":"TRC_3GGM4N","points":3.5,"dsr_gain":-16.25},{"pos":11,"slug":"johnny-law","driver":"Johnny Law","points":3,"dsr_gain":3.5},{"pos":12,"slug":"gbrc-trevor-74","driver":"GBRC-Trevor-74","points":2.5,"dsr_gain":-2.75},{"pos":13,"slug":"jasonkhan","driver":"Jasonkhan","points":2,"dsr_gain":-9},{"pos":0,"slug":"trc-saf1","driver":"TRC@SAF1","points":0,"dsr_gain":0},{"pos":0,"slug":"cracked-canoe","driver":"Cracked-Canoe","points":0,"dsr_gain":0}],"biggest_dsr_gain":{"slug":"piece-duke","driver":"piece-duke","value":17.5}}]}