{"driver":"Bee","slug":"bee","first_seen":"2026-02-07","events_count":10,"current":{"lpr":70.4,"dsr":1059.2,"lpr_pos":61,"dsr_pos":58},"bests":{"best_dsr":1059.2,"best_lpr":70.4,"best_lpr_pos":56,"best_dsr_pos":51},"history":[{"date":"2026-02-07","event":"Championship S5 - Round 1 - CGV - Tier B","tier":"B","position":11,"final_points":4.8,"dsr":1004.4,"lpr":4.8},{"date":"2026-02-14","event":"Championship S5 - Round 2 - Blue Moon - Tier B","tier":"B","position":12,"final_points":4,"dsr":1010.4,"lpr":8.8},{"date":"2026-02-21","event":"Championship S5 - Round 3 - Road Atlanta - Tier B","tier":"B","position":9,"final_points":6.4,"dsr":1017.6,"lpr":15.2},{"date":"2026-02-28","event":"Championship S5 - Round 4 - Tsukoba - Tier B","tier":"B","position":10,"final_points":5.6,"dsr":1022.4,"lpr":20.8},{"date":"2026-03-21","event":"Championship S5 - Round 5 - Suzuka - Tier B","tier":"B","position":3,"final_points":16,"dsr":1046.4,"lpr":36.8},{"date":"2026-03-28","event":"Championship S5 - Round 6 - Kyoto - Tier B","tier":"B","position":7,"final_points":9.6,"dsr":1053.2,"lpr":46.4},{"date":"2026-04-04","event":"Championship S5 - Round 7 - St. Croix - Tier B","tier":"B","position":9,"final_points":6.4,"dsr":1054.4,"lpr":52.8},{"date":"2026-04-11","event":"Championship S5 - Finale - Abu Dhabi - Tier B","tier":"B","position":9,"final_points":6.4,"dsr":1057.6,"lpr":59.2},{"date":"2026-06-13","event":"CS S6 - Dragon Trail Seaside Reverse - Tier B","tier":"B","position":13,"final_points":3.2,"dsr":1053.2,"lpr":62.4},{"date":"2026-06-20","event":"CS S6 - Lago Maggiore Full Course Reverse - Tier B","tier":"B","position":8,"final_points":8,"dsr":1059.2,"lpr":70.4}]}