{"driver":"Flavio gavatorie","slug":"flavio-gavatorie","first_seen":"2025-12-05","events_count":10,"lpr":88.5,"dsr":1098.25,"lpr_pos":53,"dsr_pos":42,"lpr_trend":0,"dsr_trend":-1,"points_per_race":8.85,"bests":{"best_lpr":88.5,"best_dsr":1105.75,"best_lpr_pos":35,"best_dsr_pos":4},"stats":{"wins":2,"podiums":3,"top5":5,"best_finish":1,"avg_finish":6,"points_per_race":8.85,"recent_form":[12,4,1,15,1],"biggest_dsr_gain":{"value":54,"date":"2026-01-24","event":"5h Le Mans Showdown","tier":"A"},"biggest_lpr_gain":{"value":28,"date":"2026-01-24","event":"5h Le Mans Showdown","tier":"A"},"consistency":4.27,"giant_kills":50},"division":{"current":"A","progression":[{"tier":"A","from":"2026-01-24"}]},"badges":["giant_killer","division_a","race_winner","veteran"],"history":[{"date":"2025-12-05","event":"Spec 3 Friday EU - Race 1","tier":"3x3","position":6,"final_points":3.5,"dsr":1019.75,"lpr":3.5,"dsr_gain":19.75,"lpr_gain":3.5},{"date":"2025-12-05","event":"Spec 3 Friday EU - Race 2","tier":"3x3","position":7,"final_points":3,"dsr":1031.25,"lpr":6.5,"dsr_gain":11.5,"lpr_gain":3},{"date":"2025-12-06","event":"Spec 3 Friday US - Race 1","tier":"3x3","position":3,"final_points":5,"dsr":1045.75,"lpr":11.5,"dsr_gain":14.5,"lpr_gain":5},{"date":"2025-12-06","event":"Spec 3 Friday US - Race 2","tier":"3x3","position":5,"final_points":4,"dsr":1051.75,"lpr":15.5,"dsr_gain":6,"lpr_gain":4},{"date":"2025-12-08","event":"Miata Monday Lago Maggiore EU","tier":"Cup","position":6,"final_points":7,"dsr":1051.25,"lpr":22.5,"dsr_gain":-0.5,"lpr_gain":7},{"date":"2025-12-09","event":"Miata Monday Lago Maggiore Americas","tier":"Cup","position":1,"final_points":14,"dsr":1066.25,"lpr":36.5,"dsr_gain":15,"lpr_gain":14},{"date":"2025-12-23","event":"Miata Monday FINALE Americas","tier":"Cup","position":15,"final_points":1,"dsr":1046.75,"lpr":37.5,"dsr_gain":-19.5,"lpr_gain":1},{"date":"2026-01-24","event":"5h Le Mans Showdown","tier":"A","position":1,"final_points":28,"dsr":1100.75,"lpr":65.5,"dsr_gain":54,"lpr_gain":28},{"date":"2026-01-31","event":"1,5h Lemons Special","tier":"A","position":4,"final_points":18,"dsr":1105.75,"lpr":83.5,"dsr_gain":5,"lpr_gain":18},{"date":"2026-05-23","event":"8h Nürburgring Endurance","tier":"A","position":12,"final_points":5,"dsr":1098.25,"lpr":88.5,"dsr_gain":-7.5,"lpr_gain":5}]}