{"driver":"pafflique","slug":"pafflique","first_seen":"2025-10-14","events_count":4,"lpr":20.5,"dsr":1034.25,"lpr_pos":111,"dsr_pos":79,"lpr_trend":-2,"dsr_trend":0,"current":{"lpr":20.5,"dsr":1034.25,"lpr_pos":111,"dsr_pos":79},"points_per_race":5.13,"bests":{"best_lpr":20.5,"best_dsr":1034.25,"best_lpr_pos":48,"best_dsr_pos":38},"stats":{"wins":0,"podiums":0,"top5":1,"best_finish":5,"avg_finish":9,"points_per_race":5.13,"recent_form":[7,10,5,14],"biggest_dsr_gain":{"value":18,"date":"2025-12-01","event":"Miata Monday Brands EU","tier":"Cup"},"biggest_lpr_gain":{"value":8,"date":"2025-12-01","event":"Miata Monday Brands EU","tier":"Cup"},"consistency":null,"giant_kills":15},"division":{"current":"A","progression":[{"tier":"A","from":"2025-10-14"}]},"badges":["division_a","veteran"],"history":[{"date":"2025-10-14","event":"Championship Tier A","tier":"A","position":14,"final_points":3,"dsr":1001.5,"lpr":3,"dsr_gain":1.5,"lpr_gain":3},{"date":"2025-12-01","event":"Miata Monday Brands EU","tier":"Cup","position":5,"final_points":8,"dsr":1019.5,"lpr":11,"dsr_gain":18,"lpr_gain":8},{"date":"2025-12-15","event":"Miata Monday Autopolis EU","tier":"Cup","position":10,"final_points":3.5,"dsr":1019.25,"lpr":14.5,"dsr_gain":-0.25,"lpr_gain":3.5},{"date":"2025-12-22","event":"Miata Monday FINALE EU","tier":"Cup","position":7,"final_points":6,"dsr":1034.25,"lpr":20.5,"dsr_gain":15,"lpr_gain":6}]}