{"driver":"Paiute24","slug":"paiute24","first_seen":"2026-06-13","events_count":2,"lpr":6.4,"dsr":1011.2,"lpr_pos":150,"dsr_pos":128,"lpr_trend":0,"dsr_trend":0,"points_per_race":3.2,"bests":{"best_lpr":6.4,"best_dsr":1011.2,"best_lpr_pos":147,"best_dsr_pos":123},"stats":{"wins":0,"podiums":0,"top5":0,"best_finish":9,"avg_finish":9,"points_per_race":3.2,"recent_form":[0,9],"biggest_dsr_gain":{"value":11.2,"date":"2026-06-13","event":"CS S6 - Dragon Trail Seaside Reverse - Tier B","tier":"B"},"biggest_lpr_gain":{"value":6.4,"date":"2026-06-13","event":"CS S6 - Dragon Trail Seaside Reverse - Tier B","tier":"B"},"consistency":null,"giant_kills":15},"division":{"current":"B","progression":[{"tier":"B","from":"2026-06-13"}]},"badges":[],"history":[{"date":"2026-06-13","event":"CS S6 - Dragon Trail Seaside Reverse - Tier B","tier":"B","position":9,"final_points":6.4,"dsr":1011.2,"lpr":6.4,"dsr_gain":11.2,"lpr_gain":6.4},{"date":"2026-06-20","event":"CS S6 - Lago Maggiore Full Course Reverse - Tier B","tier":"B","position":0,"final_points":0,"dsr":1011.2,"lpr":6.4,"dsr_gain":0,"lpr_gain":0}]}