{"driver":"TRC_Mik_ VY","slug":"trc-mik-vy","first_seen":"2025-10-14","events_count":42,"lpr":157.4,"dsr":1020.7,"lpr_pos":40,"dsr_pos":100,"lpr_trend":0,"dsr_trend":-1,"current":{"lpr":157.4,"dsr":1020.7,"lpr_pos":40,"dsr_pos":100},"points_per_race":3.75,"bests":{"best_lpr":157.4,"best_dsr":1045.45,"best_lpr_pos":40,"best_dsr_pos":41},"stats":{"wins":0,"podiums":1,"top5":3,"best_finish":3,"avg_finish":9.9,"points_per_race":3.75,"recent_form":[13,3,7,14,4],"biggest_dsr_gain":{"value":17.5,"date":"2026-05-23","event":"8h Nürburgring Endurance","tier":"A"},"biggest_lpr_gain":{"value":10,"date":"2026-06-24","event":"Yaris Wednesday - Brands Hatch Indy Circuit - EU","tier":"Cup"},"consistency":2.53,"giant_kills":30},"division":{"current":"C","progression":[{"tier":"B","from":"2025-10-14"},{"tier":"C","from":"2025-11-01"},{"tier":"A","from":"2026-01-24"},{"tier":"B","from":"2026-03-14"},{"tier":"A","from":"2026-05-23"},{"tier":"C","from":"2026-06-13"}]},"badges":["giant_killer","division_a","veteran"],"history":[{"date":"2025-10-14","event":"Endurance Fuji Tier B","tier":"B","position":11,"final_points":4.8,"dsr":1002.4,"lpr":4.8,"dsr_gain":2.4,"lpr_gain":4.8},{"date":"2025-11-01","event":"2h Endurance Road Atlanta","tier":"C","position":11,"final_points":3.6,"dsr":996.2,"lpr":8.4,"dsr_gain":-6.2,"lpr_gain":3.6},{"date":"2026-01-10","event":"Drivetrain Friday R1 US","tier":"3x3","position":13,"final_points":1,"dsr":996.7,"lpr":9.4,"dsr_gain":0.5,"lpr_gain":1},{"date":"2026-01-10","event":"Drivetrain Friday R2 US","tier":"3x3","position":13,"final_points":1,"dsr":997.2,"lpr":10.4,"dsr_gain":0.5,"lpr_gain":1},{"date":"2026-01-10","event":"Drivetrain Friday R3 US","tier":"3x3","position":11,"final_points":1.5,"dsr":997.95,"lpr":11.9,"dsr_gain":0.75,"lpr_gain":1.5},{"date":"2026-01-17","event":"Fun Friday Lago Maggiore US","tier":"3x3","position":14,"final_points":0.75,"dsr":999.45,"lpr":12.65,"dsr_gain":0.38,"lpr_gain":0.75},{"date":"2026-01-17","event":"Fun Friday Alsace US","tier":"3x3","position":13,"final_points":1,"dsr":998.45,"lpr":13.65,"dsr_gain":0.5,"lpr_gain":1},{"date":"2026-01-17","event":"Fun Friday Eiger Nordwand US","tier":"3x3","position":12,"final_points":1.25,"dsr":999.08,"lpr":14.9,"dsr_gain":0.63,"lpr_gain":1.25},{"date":"2026-01-17","event":"Fun Friday Suzuka US","tier":"3x3","position":8,"final_points":2.5,"dsr":1004.7,"lpr":17.4,"dsr_gain":5.25,"lpr_gain":2.5},{"date":"2026-01-20","event":"Radical Cup - R3 - US","tier":"Cup","position":12,"final_points":2.5,"dsr":1003.95,"lpr":19.9,"dsr_gain":-0.75,"lpr_gain":2.5},{"date":"2026-01-24","event":"5h Le Mans Showdown","tier":"A","position":14,"final_points":3,"dsr":1007.45,"lpr":22.9,"dsr_gain":3.5,"lpr_gain":3},{"date":"2026-02-10","event":"Radical Cup - R6 - Americas","tier":"Cup","position":12,"final_points":2.5,"dsr":1004.7,"lpr":25.4,"dsr_gain":-2.75,"lpr_gain":2.5},{"date":"2026-03-07","event":"Special Event - 40 laps of Spa - Lobby 2","tier":"Cup","position":9,"final_points":4,"dsr":1004.7,"lpr":29.4,"dsr_gain":0,"lpr_gain":4},{"date":"2026-03-10","event":"M2 Cup - Round 4 - Spa - Americas","tier":"Cup","position":10,"final_points":3.5,"dsr":1006.45,"lpr":32.9,"dsr_gain":1.75,"lpr_gain":3.5},{"date":"2026-03-14","event":"2h Radical Endurance - Barcelona - Tier B","tier":"B","position":0,"final_points":0,"dsr":1006.45,"lpr":32.9,"dsr_gain":0,"lpr_gain":0},{"date":"2026-04-07","event":"Mini Monday - Tsukuba - Americas","tier":"Cup","position":12,"final_points":2.5,"dsr":1007.7,"lpr":35.4,"dsr_gain":1.25,"lpr_gain":2.5},{"date":"2026-04-22","event":"GR86 Spec Series - Tokyo Expressway - EU","tier":"Cup","position":9,"final_points":4,"dsr":1011.7,"lpr":39.4,"dsr_gain":4,"lpr_gain":4},{"date":"2026-04-23","event":"GR86 Spec Series - Tokyo Expressway - Americas","tier":"Cup","position":10,"final_points":3.5,"dsr":1013.45,"lpr":42.9,"dsr_gain":1.75,"lpr_gain":3.5},{"date":"2026-04-27","event":"Mini Monday - Kyoto Driving Park - EU","tier":"Cup","position":11,"final_points":3,"dsr":1018.95,"lpr":45.9,"dsr_gain":5.5,"lpr_gain":3},{"date":"2026-04-29","event":"GR86 Spec Series - Kyoto Diving Park - EU","tier":"Cup","position":10,"final_points":3.5,"dsr":1020.7,"lpr":49.4,"dsr_gain":1.75,"lpr_gain":3.5},{"date":"2026-05-04","event":"Mini Monday - Grand Valley - EU","tier":"Cup","position":8,"final_points":5,"dsr":1025.2,"lpr":54.4,"dsr_gain":4.5,"lpr_gain":5},{"date":"2026-05-06","event":"GR86 Spec Series - Goodwood Motor Circuit - EU","tier":"Cup","position":9,"final_points":4,"dsr":1023.2,"lpr":58.4,"dsr_gain":-2,"lpr_gain":4},{"date":"2026-05-07","event":"GR86 Spec Series - Goodwood Motor Circuit - Americas","tier":"Cup","position":9,"final_points":4,"dsr":1021.2,"lpr":62.4,"dsr_gain":-2,"lpr_gain":4},{"date":"2026-05-11","event":"Mini Monday - Tokyo Expressway - EU","tier":"Cup","position":5,"final_points":8,"dsr":1025.2,"lpr":70.4,"dsr_gain":4,"lpr_gain":8},{"date":"2026-05-13","event":"GR86 Spec Series - Monza - EU","tier":"Cup","position":9,"final_points":4,"dsr":1027.2,"lpr":74.4,"dsr_gain":2,"lpr_gain":4},{"date":"2026-05-20","event":"GR86 Spec Series - Willow Springs - EU","tier":"Cup","position":10,"final_points":3.5,"dsr":1024.95,"lpr":77.9,"dsr_gain":-2.25,"lpr_gain":3.5},{"date":"2026-05-23","event":"8h Nürburgring Endurance","tier":"A","position":10,"final_points":7,"dsr":1042.45,"lpr":84.9,"dsr_gain":17.5,"lpr_gain":7},{"date":"2026-05-25","event":"Miata Mondays - Watkins Glen - EU","tier":"Cup","position":10,"final_points":3.5,"dsr":1040.2,"lpr":88.4,"dsr_gain":-2.25,"lpr_gain":3.5},{"date":"2026-05-27","event":"GR86 Spec Series - Grand Valley - EU","tier":"Cup","position":10,"final_points":3.5,"dsr":1039.95,"lpr":91.9,"dsr_gain":-0.25,"lpr_gain":3.5},{"date":"2026-06-01","event":"Miata Mondays - Dragon Trail - EU","tier":"Cup","position":8,"final_points":5,"dsr":1042.45,"lpr":96.9,"dsr_gain":2.5,"lpr_gain":5},{"date":"2026-06-03","event":"GR86 Spec Series - Nürburgring - EU","tier":"Cup","position":8,"final_points":5,"dsr":1042.95,"lpr":101.9,"dsr_gain":0.5,"lpr_gain":5},{"date":"2026-06-08","event":"Miata Mondays - Willow Springs - EU","tier":"Cup","position":11,"final_points":3,"dsr":1040.45,"lpr":104.9,"dsr_gain":-2.5,"lpr_gain":3},{"date":"2026-06-10","event":"Yaris Wednesday - Suzuka Circuit East - EU","tier":"Cup","position":7,"final_points":6,"dsr":1045.45,"lpr":110.9,"dsr_gain":5,"lpr_gain":6},{"date":"2026-06-12","event":"Friday FF Cup - Deep Forest - EU","tier":"Cup","position":8,"final_points":5,"dsr":1039.7,"lpr":115.9,"dsr_gain":0.5,"lpr_gain":5},{"date":"2026-06-12","event":"Friday FF Cup - Deep Forest - Americas","tier":"Cup","position":10,"final_points":3.5,"dsr":1039.2,"lpr":119.4,"dsr_gain":-6.25,"lpr_gain":3.5},{"date":"2026-06-13","event":"CS S6 - Dragon Trail Seaside Reverse - Tier C","tier":"C","position":10,"final_points":4.2,"dsr":1029.8,"lpr":123.6,"dsr_gain":-9.9,"lpr_gain":4.2},{"date":"2026-06-15","event":"Miata Mondays - Sardegna Road Track - EU","tier":"Cup","position":8,"final_points":5,"dsr":1032.3,"lpr":128.6,"dsr_gain":2.5,"lpr_gain":5},{"date":"2026-06-17","event":"Yaris Wednesday - Barcelona Rallycross - EU","tier":"Cup","position":4,"final_points":9,"dsr":1034.8,"lpr":137.6,"dsr_gain":2.5,"lpr_gain":9},{"date":"2026-06-20","event":"CS S6 - Lago Maggiore Full Course Reverse - Tier C","tier":"C","position":14,"final_points":1.8,"dsr":1013.7,"lpr":139.4,"dsr_gain":-21.1,"lpr_gain":1.8},{"date":"2026-06-22","event":"Miata Mondays - Tokyo Expressway Central Clockwise - EU","tier":"Cup","position":7,"final_points":6,"dsr":1016.7,"lpr":145.4,"dsr_gain":3,"lpr_gain":6},{"date":"2026-06-24","event":"Yaris Wednesday - Brands Hatch Indy Circuit - EU","tier":"Cup","position":3,"final_points":10,"dsr":1021.7,"lpr":155.4,"dsr_gain":5,"lpr_gain":10},{"date":"2026-06-26","event":"Friday FF Cup - High Speed Ring - EU","tier":"Cup","position":13,"final_points":2,"dsr":1020.7,"lpr":157.4,"dsr_gain":-1,"lpr_gain":2}]}